gif_conv_ysc/__init__.py
gif_conv_ysc/converter.py
gif_conv_ysc-1.0.1.dist-info/LICENSE
gif_conv_ysc-1.0.1.dist-info/METADATA
gif_conv_ysc-1.0.1.dist-info/WHEEL
gif_conv_ysc-1.0.1.dist-info/top_level.txt
gif_conv_ysc-1.0.1.dist-info/RECORD
