Metadata-Version: 2.1
Name: gif-conv-ysc
Version: 1.0.1
Summary: Test package for distribution
Home-page: UNKNOWN
Author: Yooseong Choi
Author-email: choiys3574@naver.com
License: UNKNOWN
Keywords: GIFCONVERTER,gifconverter
Platform: UNKNOWN
Classifier: Programming Language :: Python :: 3.9
Classifier: License :: OSI Approved :: MIT License
Classifier: Operating System :: OS Independent
Requires-Python: >=3.9
License-File: LICENSE
Requires-Dist: pillow
